itto_yolo_tool/__init__.py
itto_yolo_tool/main.py
itto_yolo_tool/resource_rc.py
itto_yolo_tool/tools/__init__.py
itto_yolo_tool/tools/xml_convert_examine.py
itto_yolo_tool/tools/xml_to_txt.py
itto_yolo_tool/tools/rolabelimg-fix/.gitignore
itto_yolo_tool/tools/rolabelimg-fix/.travis.yml
itto_yolo_tool/tools/rolabelimg-fix/HISTORY.rst
itto_yolo_tool/tools/rolabelimg-fix/MANIFEST.in
itto_yolo_tool/tools/rolabelimg-fix/Makefile
itto_yolo_tool/tools/rolabelimg-fix/README.rst
itto_yolo_tool/tools/rolabelimg-fix/__init__.py
itto_yolo_tool/tools/rolabelimg-fix/issue_template.md
itto_yolo_tool/tools/rolabelimg-fix/resources.py
itto_yolo_tool/tools/rolabelimg-fix/resources.qrc
itto_yolo_tool/tools/rolabelimg-fix/roLabelImg.py
itto_yolo_tool/tools/rolabelimg-fix/setup.cfg
itto_yolo_tool/tools/rolabelimg-fix/setup.py
itto_yolo_tool/tools/rolabelimg-fix/__pycache__/resources.cpython-311.pyc
itto_yolo_tool/tools/rolabelimg-fix/build-tools/.gitignore
itto_yolo_tool/tools/rolabelimg-fix/build-tools/build-for-pypi.sh
itto_yolo_tool/tools/rolabelimg-fix/build-tools/build-ubuntu-binary.sh
itto_yolo_tool/tools/rolabelimg-fix/build-tools/build-windows-binary.sh
itto_yolo_tool/tools/rolabelimg-fix/build-tools/envsetup.sh
itto_yolo_tool/tools/rolabelimg-fix/data/predefined_classes.txt
itto_yolo_tool/tools/rolabelimg-fix/icons/cancel.png
itto_yolo_tool/tools/rolabelimg-fix/icons/close.png
itto_yolo_tool/tools/rolabelimg-fix/icons/color.png
itto_yolo_tool/tools/rolabelimg-fix/icons/color_line.png
itto_yolo_tool/tools/rolabelimg-fix/icons/copy.png
itto_yolo_tool/tools/rolabelimg-fix/icons/delete.png
itto_yolo_tool/tools/rolabelimg-fix/icons/done.png
itto_yolo_tool/tools/rolabelimg-fix/icons/done.svg
itto_yolo_tool/tools/rolabelimg-fix/icons/edit.png
itto_yolo_tool/tools/rolabelimg-fix/icons/expert1.png
itto_yolo_tool/tools/rolabelimg-fix/icons/expert2.png
itto_yolo_tool/tools/rolabelimg-fix/icons/eye.png
itto_yolo_tool/tools/rolabelimg-fix/icons/feBlend-icon.png
itto_yolo_tool-2.0.1.dist-info/LICENSE
itto_yolo_tool-2.0.1.dist-info/METADATA
itto_yolo_tool-2.0.1.dist-info/WHEEL
itto_yolo_tool-2.0.1.dist-info/entry_points.txt
itto_yolo_tool-2.0.1.dist-info/top_level.txt
itto_yolo_tool-2.0.1.dist-info/RECORD
