Metadata-Version: 2.2
Name: itto-yolo-tool
Version: 2.0.1
Summary: A integrated GUI tool for YOLO model training and annotation
Home-page: https://github.com/RinST-Dreaming/Yolo-integrated-training-tool
Author: rinst
Author-email: 544250926@qq.com
Classifier: Programming Language :: Python :: 3
Classifier: License :: OSI Approved :: MIT License
Classifier: Operating System :: OS Independent
Requires-Python: >=3.7
License-File: LICENSE
Requires-Dist: PyQt5>=5.15.0
Requires-Dist: opencv-python>=4.5.0
Requires-Dist: numpy>=1.21.0
Dynamic: author
Dynamic: author-email
Dynamic: classifier
Dynamic: description
Dynamic: description-content-type
Dynamic: home-page
Dynamic: requires-dist
Dynamic: requires-python
Dynamic: summary
